{
  "format": "zil.release-request.v0.1",
  "release_id": "release:demo-v1",
  "module": "Demo",
  "artifacts": [
    {
      "path": "workflow/Demo.lean",
      "sha256": "sha256:f6bd2a33b683e4149cf9c5ea68553184a57ca1edcdda304700fa124708a5b931"
    }
  ],
  "evidence": {
    "workflow": {
      "path": "evidence/workflow.json",
      "artifact": "workflow/Demo.lean",
      "minimum_actions": 1
    },
    "proof_tokens": {
      "path": "evidence/proof.json"
    },
    "theorem_locks": {
      "path": "evidence/locks.json"
    },
    "authorization": {
      "path": "evidence/authorization.txt",
      "object": "repo.release",
      "relation": "zil.publisher",
      "subject": "agent.release"
    },
    "formalization": {
      "path": "evidence/formalization.txt",
      "required_targets": ["foundations"]
    }
  }
}
